{
  "name": "DwFeed",
  "plural": "dwFeeds",
  "base": "PersistedModel",
  "idInjection": true,
  "options": {
    "validateUpsert": true
  },
  "properties": {
    "name": {
      "type": "string",
      "required": true
    },
    "index": {
      "type": "string"
    },
    "feedUrl": {
      "type": "string"
    },
    "credentials": {
      "type": "string"
    },
    "protocol": {
      "type": "string"
    },
    "transmissions": {
      "type": [
        "string"
      ]
    }
  },
  "validations": [],
  "relations": {
    "domains": {
      "type": "hasAndBelongsToMany",
      "model": "DwDomain"
    },
    "teams": {
      "type": "hasAndBelongsToMany",
      "model": "DwTeam"
    },
    "trails": {
      "type": "hasAndBelongsToMany",
      "model": "DwTrail"
    },
    "serviceType": {
      "type": "belongsTo",
      "model": "DwServiceType",
      "foreignKey": "dwServiceTypeId"
    },
    "transmissions": {
      "type": "hasMany",
      "model": "DwTransmission",
      "foreignKey": "dwFeedId"
    }
  },
  "acls": [],
  "methods": {}
}
